LICENSE
MANIFEST.in
README.rst
setup.cfg
setup.py
elasticapm/__init__.py
elasticapm/base.py
elasticapm/events.py
elasticapm/middleware.py
elasticapm/processors.py
elasticapm/traces.py
elasticapm/version.py
elasticapm/conf/__init__.py
elasticapm/conf/constants.py
elasticapm/context/__init__.py
elasticapm/context/base.py
elasticapm/context/contextvars.py
elasticapm/context/threadlocal.py
elasticapm/contrib/__init__.py
elasticapm/contrib/async_worker.py
elasticapm/contrib/paste.py
elasticapm/contrib/celery/__init__.py
elasticapm/contrib/django/__init__.py
elasticapm/contrib/django/apps.py
elasticapm/contrib/django/client.py
elasticapm/contrib/django/context_processors.py
elasticapm/contrib/django/handlers.py
elasticapm/contrib/django/utils.py
elasticapm/contrib/django/celery/__init__.py
elasticapm/contrib/django/celery/models.py
elasticapm/contrib/django/management/__init__.py
elasticapm/contrib/django/management/commands/__init__.py
elasticapm/contrib/django/management/commands/elasticapm.py
elasticapm/contrib/django/middleware/__init__.py
elasticapm/contrib/django/middleware/wsgi.py
elasticapm/contrib/flask/__init__.py
elasticapm/contrib/flask/utils.py
elasticapm/contrib/opentracing/__init__.py
elasticapm/contrib/opentracing/span.py
elasticapm/contrib/opentracing/tracer.py
elasticapm/contrib/pylons/__init__.py
elasticapm/contrib/rq/__init__.py
elasticapm/contrib/twisted/__init__.py
elasticapm/contrib/zerorpc/__init__.py
elasticapm/handlers/__init__.py
elasticapm/handlers/logbook.py
elasticapm/handlers/logging.py
elasticapm/instrumentation/__init__.py
elasticapm/instrumentation/control.py
elasticapm/instrumentation/register.py
elasticapm/instrumentation/packages/__init__.py
elasticapm/instrumentation/packages/base.py
elasticapm/instrumentation/packages/botocore.py
elasticapm/instrumentation/packages/cassandra.py
elasticapm/instrumentation/packages/dbapi2.py
elasticapm/instrumentation/packages/elasticsearch.py
elasticapm/instrumentation/packages/jinja2.py
vtp_elastic_apm.egg-info/PKG-INFO
vtp_elastic_apm.egg-info/SOURCES.txt
vtp_elastic_apm.egg-info/dependency_links.txt
vtp_elastic_apm.egg-info/entry_points.txt
vtp_elastic_apm.egg-info/not-zip-safe
vtp_elastic_apm.egg-info/requires.txt
vtp_elastic_apm.egg-info/top_level.txt