Metadata-Version: 2.1
Name: vtp-elastic-apm
Version: 5.1.1
Summary: The official Python module for Elastic APM
Home-page: https://github.com/hero1796/apm-agent-python.git
Author: hero1796
License: BSD
Platform: UNKNOWN
Classifier: Intended Audience :: Developers
Classifier: Intended Audience :: System Administrators
Classifier: Operating System :: OS Independent
Classifier: Topic :: Software Development
Classifier: Programming Language :: Python
Classifier: Programming Language :: Python :: 2.7
Classifier: Programming Language :: Python :: 3.3
Classifier: Programming Language :: Python :: 3.4
Classifier: Programming Language :: Python :: 3.5
Classifier: Programming Language :: Python :: 3.6
Classifier: Programming Language :: Python :: Implementation :: CPython
Classifier: Programming Language :: Python :: Implementation :: PyPy
Provides-Extra: flask
Provides-Extra: asyncio
Provides-Extra: tests
Provides-Extra: opentracing
